pyThorlabsAPT/__init__.py
pyThorlabsAPT/driver.py
pyThorlabsAPT/main.py
pyThorlabsAPT/graphics/pause.png
pyThorlabsAPT/graphics/play.png
pyThorlabsAPT/graphics/refresh.png
pyThorlabsAPT/graphics/stop.png
pyThorlabsAPT/thorlabs_apt/APT.dll
pyThorlabsAPT/thorlabs_apt/_APTAPI.py
pyThorlabsAPT/thorlabs_apt/__init__.py
pyThorlabsAPT/thorlabs_apt/_error_codes.py
pyThorlabsAPT/thorlabs_apt/core.py
pyThorlabsAPT-0.2.dist-info/METADATA
pyThorlabsAPT-0.2.dist-info/WHEEL
pyThorlabsAPT-0.2.dist-info/entry_points.txt
pyThorlabsAPT-0.2.dist-info/top_level.txt
pyThorlabsAPT-0.21.dist-info/METADATA
pyThorlabsAPT-0.21.dist-info/WHEEL
pyThorlabsAPT-0.21.dist-info/entry_points.txt
pyThorlabsAPT-0.21.dist-info/top_level.txt
pyThorlabsAPT-0.21.dist-info/RECORD
