Metadata-Version: 2.1
Name: pyThorlabsAPT
Version: 0.21
Summary: A python library/GUI to access and control motors via the APT protocol.
Home-page: https://github.com/MicheleCotrufo/
Author: Michele Cotrufo
Author-email: michele.cotrufo@gmail.com
License: MIT
Platform: UNKNOWN
Requires-Dist: abstract-instrument-interface
Requires-Dist: PyQt5 (>=5.15.6)
Requires-Dist: pyqtgraph
Requires-Dist: pyvisa
Requires-Dist: numpy
